taurenmd/__init__.py
taurenmd/__main__.py
taurenmd/_cli_template.py
taurenmd/cli.py
taurenmd/cli_distances.py
taurenmd/cli_fext.py
taurenmd/cli_imagemol.py
taurenmd/cli_nosol.py
taurenmd/cli_pangle.py
taurenmd/cli_report.py
taurenmd/cli_rmsd.py
taurenmd/cli_rmsf.py
taurenmd/cli_rotations.py
taurenmd/cli_trajedit.py
taurenmd/core.py
taurenmd/logger.py
taurenmd/libs/__init__.py
taurenmd/libs/libcalc.py
taurenmd/libs/libcli.py
taurenmd/libs/libio.py
taurenmd/libs/libmda.py
taurenmd/libs/libmdt.py
taurenmd/libs/libopenmm.py
taurenmd/libs/libutil.py
taurenmd/plots/__init__.py
taurenmd/plots/labeldots.py
taurenmd/plots/plotparams.py
taurenmd-0.11.2.dist-info/AUTHORS.rst
taurenmd-0.11.2.dist-info/LICENSE
taurenmd-0.11.2.dist-info/METADATA
taurenmd-0.11.2.dist-info/WHEEL
taurenmd-0.11.2.dist-info/entry_points.txt
taurenmd-0.11.2.dist-info/top_level.txt
taurenmd-0.11.2.dist-info/RECORD
