Metadata-Version: 2.1
Name: taurenmd
Version: 0.11.2
Summary: A command-line interface for analysis routines in Molecular Dynamics data.
Home-page: https://github.com/joaomcteixeira/taurenmd
Author: Joao MC Teixeira
Author-email: joaomcteixeira@gmail.com
License: GNU GPLv2
Project-URL: Documentation, https://taurenmd.readthedocs.io/
Project-URL: Changelog, https://taurenmd.readthedocs.io/en/latest/changelog.html
Project-URL: Issue Tracker, https://github.com/joaomcteixeira/taurenmd/issues
Keywords: Molecular Dynamics,Proteins,DNA,RNA,Structural Biology,Molecular Biology,Biochemistry
Platform: UNKNOWN
Classifier: Development Status :: 4 - Beta
Classifier: Intended Audience :: Developers
Classifier: Intended Audience :: Education
Classifier: Intended Audience :: Science/Research
Classifier: Topic :: Scientific/Engineering :: Bio-Informatics
Classifier: Topic :: Scientific/Engineering :: Chemistry
Classifier: License :: OSI Approved :: GNU General Public License v2 (GPLv2)
Classifier: Operating System :: Unix
Classifier: Operating System :: POSIX
Classifier: Environment :: Console
Classifier: Programming Language :: Python
Classifier: Programming Language :: Python :: 3
Classifier: Programming Language :: Python :: 3.8
Classifier: Programming Language :: Python :: 3.9
Classifier: Programming Language :: Python :: 3.10
Classifier: Topic :: Utilities
Requires-Python: >=3.8, <3.11
Provides-Extra: all
Requires-Dist: MDAnalysis (==2) ; extra == 'all'
Requires-Dist: mdtraj (<2,>=1.9) ; extra == 'all'
Requires-Dist: matplotlib (<4,>=3) ; extra == 'all'
Requires-Dist: numpy (<2,>=1) ; extra == 'all'
Provides-Extra: md
Requires-Dist: MDAnalysis (==2) ; extra == 'md'
Requires-Dist: mdtraj (<2,>=1.9) ; extra == 'md'
Provides-Extra: sup
Requires-Dist: matplotlib (<4,>=3) ; extra == 'sup'
Requires-Dist: numpy (<2,>=1) ; extra == 'sup'
